tweet2story/__init__.py
tweet2story/__main__.py
tweet2story/image_renderer.py
tweet2story/tweepy_scraper.py
tweet2story/twint_scraper.py
tweet2story-1.0.4.dist-info/LICENSE.md
tweet2story-1.0.4.dist-info/METADATA
tweet2story-1.0.4.dist-info/WHEEL
tweet2story-1.0.4.dist-info/entry_points.txt
tweet2story-1.0.4.dist-info/top_level.txt
tweet2story-1.0.4.dist-info/RECORD
